papertlab/__init__.py
papertlab/__main__.py
papertlab/args.py
papertlab/args_formatter.py
papertlab/commands.py
papertlab/create_directory_structure.py
papertlab/diffs.py
papertlab/dump.py
papertlab/flask_app.py
papertlab/format_settings.py
papertlab/help.py
papertlab/help_pats.py
papertlab/history.py
papertlab/io.py
papertlab/linter.py
papertlab/llm.py
papertlab/main.py
papertlab/mdstream.py
papertlab/models.py
papertlab/prompts.py
papertlab/repo.py
papertlab/repomap.py
papertlab/report.py
papertlab/run_cmd.py
papertlab/scrape.py
papertlab/sendchat.py
papertlab/special.py
papertlab/sql_utils.py
papertlab/urls.py
papertlab/utils.py
papertlab/versioncheck.py
papertlab/voice.py
papertlab/agents/__init__.py
papertlab/agents/ask_coder.py
papertlab/agents/autopilot_coder.py
papertlab/agents/base_coder.py
papertlab/agents/chat_chunks.py
papertlab/agents/editblock_coder.py
papertlab/agents/editblock_fenced_coder.py
papertlab/agents/editblock_func_coder.py
papertlab/agents/help_coder.py
papertlab/agents/inline_coder.py
papertlab/agents/search_replace.py
papertlab/agents/single_wholefile_func_coder.py
papertlab/agents/udiff_coder.py
papertlab/agents/wholefile_coder.py
papertlab/agents/wholefile_func_coder.py
papertlab/agents/prompts/__init__.py
papertlab/agents/prompts/ask_prompts.py
papertlab/agents/prompts/autopilot_prompts.py
papertlab/agents/prompts/base_prompts.py
papertlab/agents/prompts/editblock_fenced_prompts.py
papertlab/agents/prompts/editblock_func_prompts.py
papertlab/agents/prompts/editblock_prompts.py
papertlab/agents/prompts/help_prompts.py
papertlab/agents/prompts/inline_prompts.py
papertlab/agents/prompts/single_wholefile_func_prompts.py
papertlab/agents/prompts/udiff_prompts.py
papertlab/agents/prompts/wholefile_func_prompts.py
papertlab/agents/prompts/wholefile_prompts.py
papertlab/queries/tree-sitter-c-tags.scm
papertlab/queries/tree-sitter-c_sharp-tags.scm
papertlab/queries/tree-sitter-cpp-tags.scm
papertlab/queries/tree-sitter-elisp-tags.scm
papert_lab-1.1.4.dist-info/LICENSE.txt
papert_lab-1.1.4.dist-info/METADATA
papert_lab-1.1.4.dist-info/WHEEL
papert_lab-1.1.4.dist-info/entry_points.txt
papert_lab-1.1.4.dist-info/top_level.txt
papert_lab-1.1.4.dist-info/RECORD
