Metadata-Version: 2.1
Name: papert-lab
Version: 1.1.4
Summary: papertlab is an AI pair programmer in your browser.
Home-page: https://papert.in/
Classifier: Development Status :: 4 - Beta
Classifier: Environment :: Console
Classifier: Intended Audience :: Developers
Classifier: License :: OSI Approved :: Apache Software License
Classifier: Programming Language :: Python :: 3
Classifier: Programming Language :: Python :: 3.10
Classifier: Programming Language :: Python :: 3.11
Classifier: Programming Language :: Python :: 3.12
Classifier: Programming Language :: Python :: 3.13
Classifier: Programming Language :: Python :: 3.9
Classifier: Programming Language :: Python
Classifier: Topic :: Software Development
Requires-Python: >=3.7,<3.13
License-File: LICENSE.txt
Requires-Dist: aiohappyeyeballs==2.3.4
Requires-Dist: aiohttp==3.10.0
Requires-Dist: aiosignal==1.3.1
Requires-Dist: altair==5.3.0
Requires-Dist: annotated-types==0.7.0
Requires-Dist: anyio==4.4.0
Requires-Dist: attrs==23.2.0
Requires-Dist: backoff==2.2.1
Requires-Dist: beautifulsoup4==4.12.3
Requires-Dist: blinker==1.8.2
Requires-Dist: cachetools==5.4.0
Requires-Dist: certifi==2024.7.4
Requires-Dist: cffi==1.16.0
Requires-Dist: charset-normalizer==3.3.2
Requires-Dist: click==8.1.7
Requires-Dist: configargparse==1.7
Requires-Dist: dataclasses-json==0.6.7
Requires-Dist: deprecated==1.2.14
Requires-Dist: diff-match-patch==20230430
Requires-Dist: dirtyjson==1.0.8
Requires-Dist: diskcache==5.6.3
Requires-Dist: distro==1.9.0
Requires-Dist: filelock==3.15.4
Requires-Dist: flake8==7.1.0
Requires-Dist: flask
Requires-Dist: flask-cors
Requires-Dist: frozenlist==1.4.1
Requires-Dist: fsspec==2024.6.1
Requires-Dist: gitdb==4.0.11
Requires-Dist: gitpython==3.1.43
Requires-Dist: greenlet==3.0.3
Requires-Dist: grep-ast==0.3.3
Requires-Dist: h11==0.14.0
Requires-Dist: httpcore==1.0.5
Requires-Dist: httpx==0.27.0
Requires-Dist: huggingface-hub==0.24.5
Requires-Dist: idna==3.7
Requires-Dist: importlib-metadata<8.0.0
Requires-Dist: importlib-resources==6.4.0
Requires-Dist: jinja2==3.1.4
Requires-Dist: joblib==1.4.2
Requires-Dist: json5==0.9.25
Requires-Dist: jsonschema==4.23.0
Requires-Dist: jsonschema-specifications==2023.12.1
Requires-Dist: litellm==1.42.9
Requires-Dist: llama-index-core==0.10.59
Requires-Dist: llama-index-embeddings-huggingface==0.2.2
Requires-Dist: markdown-it-py==3.0.0
Requires-Dist: markupsafe==2.1.5
Requires-Dist: marshmallow==3.21.3
Requires-Dist: mccabe==0.7.0
Requires-Dist: mdurl==0.1.2
Requires-Dist: minijinja==2.0.1
Requires-Dist: mpmath==1.3.0
Requires-Dist: multidict==6.0.5
Requires-Dist: mypy-extensions==1.0.0
Requires-Dist: nest-asyncio==1.6.0
Requires-Dist: networkx<3.3
Requires-Dist: nltk==3.8.1
Requires-Dist: numpy<2
Requires-Dist: openai==1.37.2
Requires-Dist: packaging==24.1
Requires-Dist: pathspec==0.12.1
Requires-Dist: pexpect==4.9.0
Requires-Dist: pillow==10.4.0
Requires-Dist: playwright==1.45.1
Requires-Dist: prompt-toolkit==3.0.47
Requires-Dist: protobuf==5.27.3
Requires-Dist: pyarrow==17.0.0
Requires-Dist: pyperclip==1.9.0
Requires-Dist: pycodestyle==2.12.0
Requires-Dist: pycparser==2.22
Requires-Dist: pydantic==2.8.2
Requires-Dist: pydantic-core==2.20.1
Requires-Dist: pydeck==0.9.1
Requires-Dist: pyee==11.1.0
Requires-Dist: pyflakes==3.2.0
Requires-Dist: pygments==2.18.0
Requires-Dist: pypandoc==1.13
Requires-Dist: python-dateutil==2.9.0.post0
Requires-Dist: python-dotenv==1.0.1
Requires-Dist: pytz==2024.1
Requires-Dist: pyyaml==6.0.1
Requires-Dist: referencing==0.35.1
Requires-Dist: regex==2024.7.24
Requires-Dist: requests==2.32.3
Requires-Dist: rich==13.7.1
Requires-Dist: rpds-py==0.19.1
Requires-Dist: safetensors==0.4.3
Requires-Dist: scikit-learn==1.5.1
Requires-Dist: scipy<1.14
Requires-Dist: sentence-transformers==3.0.1
Requires-Dist: smmap==5.0.1
Requires-Dist: sniffio==1.3.1
Requires-Dist: sounddevice==0.4.7
Requires-Dist: soundfile==0.12.1
Requires-Dist: soupsieve==2.5
Requires-Dist: sqlalchemy[asyncio]==2.0.31
Requires-Dist: sympy==1.13.1
Requires-Dist: threadpoolctl==3.5.0
Requires-Dist: tiktoken==0.7.0
Requires-Dist: tokenizers==0.19.1
Requires-Dist: tqdm==4.66.4
Requires-Dist: tree-sitter==0.21.3
Requires-Dist: tree-sitter-languages==1.10.2
Requires-Dist: typing-extensions==4.12.2
Requires-Dist: typing-inspect==0.9.0
Requires-Dist: urllib3==2.2.2
Requires-Dist: watchdog
Requires-Dist: wcwidth==0.2.13
Requires-Dist: wrapt==1.16.0
Requires-Dist: yarl==1.9.4
Requires-Dist: zipp==3.19.2
